rocketcycles/__init__.py
rocketcycles/cycles.py
rocketcycles/elements.py
rocketcycles/examples.py
rocketcycles/fluid.py
rocketcycles-0.1.dist-info/LICENSE
rocketcycles-0.1.dist-info/METADATA
rocketcycles-0.1.dist-info/WHEEL
rocketcycles-0.1.dist-info/top_level.txt
rocketcycles-0.1.dist-info/RECORD
